setup.py
writing_style/__init__.py
writing_style/analyzer.py
writing_style/similarity.py
writing_style.egg-info/PKG-INFO
writing_style.egg-info/SOURCES.txt
writing_style.egg-info/dependency_links.txt
writing_style.egg-info/top_level.txt