Metadata-Version: 1.1
Name: writing-style
Version: 0.0.6
Summary: Analyze text
Home-page: https://github.com/sergeio/writing_style
Author: Sergei Orlov
Author-email: UNKNOWN
License: BSD
Platform: UNKNOWN
Classifier: Development Status :: 2 - Pre-Alpha
Classifier: Intended Audience :: Developers
Classifier: License :: OSI Approved :: BSD License
Classifier: Operating System :: MacOS :: MacOS X
Classifier: Operating System :: POSIX
Classifier: Programming Language :: Python
